.landscape.yml
.travis.yml
AUTHORS
ChangeLog
LICENSE.txt
README.md
setup.cfg
setup.py
mutants/__init__.py
mutants/classhopper_mutant.py
mutants/immutable_mutant.py
mutants/on_access_mutant.py
mutants/special_methods.py
mutants.egg-info/PKG-INFO
mutants.egg-info/SOURCES.txt
mutants.egg-info/dependency_links.txt
mutants.egg-info/not-zip-safe
mutants.egg-info/pbr.json
mutants.egg-info/requires.txt
mutants.egg-info/top_level.txt
tests/test_classhopper_mutant.py
tests/test_immutable_mutant.py
tests/test_many_objects.py
tests/test_on_access_mutant.py