Metadata-Version: 1.1
Name: mutants
Version: 0.0.2
Summary: mutants, a Python library for objects that mutate on access
Home-page: https://github.com/t184256/mutants
Author: Alexander Sosedkin
Author-email: monk@unboiled.info
License: MIT
Keywords: hacks
Platform: UNKNOWN
Classifier: Development Status :: 2 - Pre-Alpha
Classifier: Intended Audience :: Developers
Classifier: Intended Audience :: Information Technology
Classifier: License :: OSI Approved :: MIT License
Classifier: Operating System :: OS Independent
Classifier: Programming Language :: Python
Classifier: Programming Language :: Python :: 3 :: Only
